quantastor/__init__.py
quantastor/qs_client.py
quantastor_pyclient-0.0.0.data/scripts/qs_client.py
quantastor_pyclient-0.0.0.dist-info/LICENSE
quantastor_pyclient-0.0.0.dist-info/METADATA
quantastor_pyclient-0.0.0.dist-info/WHEEL
quantastor_pyclient-0.0.0.dist-info/top_level.txt
quantastor_pyclient-0.0.0.dist-info/RECORD
