Metadata-Version: 2.1
Name: quantastor-pyclient
Version: 0.0.0
Summary: QuantaStor REST API python library
Home-page: https://github.com/OSNEXUS/QSPyClient
Author: OSNEXUS Corporation
Author-email: support@osnexus.com
License: UNKNOWN
Platform: UNKNOWN
Classifier: Programming Language :: Python :: 3
Classifier: License :: OSI Approved :: BSD License
Classifier: Operating System :: OS Independent
